odoo8_addon_account_balance_reporting_xls-8.0.1.0.0.99.dev21-py3.6-nspkg.pth
odoo_addons/account_balance_reporting_xls/README.rst
odoo_addons/account_balance_reporting_xls/__init__.py
odoo_addons/account_balance_reporting_xls/__openerp__.py
odoo_addons/account_balance_reporting_xls/i18n/account_balance_reporting_xls.pot
odoo_addons/account_balance_reporting_xls/i18n/bg.po
odoo_addons/account_balance_reporting_xls/i18n/ca.po
odoo_addons/account_balance_reporting_xls/i18n/ca_ES.po
odoo_addons/account_balance_reporting_xls/i18n/cs.po
odoo_addons/account_balance_reporting_xls/i18n/en_US.po
odoo_addons/account_balance_reporting_xls/i18n/es.po
odoo_addons/account_balance_reporting_xls/i18n/es_CR.po
odoo_addons/account_balance_reporting_xls/i18n/eu.po
odoo_addons/account_balance_reporting_xls/i18n/fr.po
odoo_addons/account_balance_reporting_xls/i18n/gl.po
odoo_addons/account_balance_reporting_xls/i18n/hr.po
odoo_addons/account_balance_reporting_xls/i18n/nl.po
odoo_addons/account_balance_reporting_xls/i18n/pl.po
odoo_addons/account_balance_reporting_xls/i18n/pt.po
odoo_addons/account_balance_reporting_xls/i18n/pt_BR.po
odoo_addons/account_balance_reporting_xls/i18n/ru.po
odoo_addons/account_balance_reporting_xls/i18n/sl.po
odoo_addons/account_balance_reporting_xls/i18n/sv.po
odoo_addons/account_balance_reporting_xls/i18n/tr.po
odoo_addons/account_balance_reporting_xls/i18n/vi.po
odoo_addons/account_balance_reporting_xls/models/__init__.py
odoo_addons/account_balance_reporting_xls/models/account_balance_reporting.py
odoo_addons/account_balance_reporting_xls/report/__init__.py
odoo_addons/account_balance_reporting_xls/report/reporting.py
odoo_addons/account_balance_reporting_xls/report/reporting_xls.py
odoo_addons/account_balance_reporting_xls/static/description/icon.png
odoo_addons/account_balance_reporting_xls/static/description/icon.svg
odoo_addons/account_balance_reporting_xls/wizard/__init__.py
odoo8_addon_account_balance_reporting_xls-8.0.1.0.0.99.dev21.dist-info/METADATA
odoo8_addon_account_balance_reporting_xls-8.0.1.0.0.99.dev21.dist-info/WHEEL
odoo8_addon_account_balance_reporting_xls-8.0.1.0.0.99.dev21.dist-info/namespace_packages.txt
odoo8_addon_account_balance_reporting_xls-8.0.1.0.0.99.dev21.dist-info/top_level.txt
odoo8_addon_account_balance_reporting_xls-8.0.1.0.0.99.dev21.dist-info/RECORD
