Metadata-Version: 2.1
Name: odoo8-addon-account-balance-reporting-xls
Version: 8.0.1.0.0.99.dev21
Summary: Account balance reporting to XLS
Home-page: http://odoo-spain.org
Author: Spanish Localization Team,Odoo Community Association (OCA)
Author-email: support@odoo-community.org
License: UNKNOWN
Platform: UNKNOWN
Classifier: Programming Language :: Python
Classifier: Framework :: Odoo
Requires-Python: ~=2.7
Requires-Dist: odoo8-addon-account-balance-reporting
Requires-Dist: odoo8-addon-report-xls
Requires-Dist: odoo (<9.0a,>=8.0a)
Requires-Dist: xlwt
